MANIFEST.in
README.md
setup.py
deus_state_machina/__init__.py
deus_state_machina/fields.py
deus_state_machina/signals.py
deus_state_machina/tasks.py
deus_state_machina/utils.py
deus_state_machina.egg-info/PKG-INFO
deus_state_machina.egg-info/SOURCES.txt
deus_state_machina.egg-info/dependency_links.txt
deus_state_machina.egg-info/not-zip-safe
deus_state_machina.egg-info/top_level.txt
tests/__init__.py
tests/settings.py
tests/urls.py
tests/wsgi.py
tests/testapp/__init__.py
tests/testapp/apps.py
tests/testapp/models.py
tests/testapp/migrations/0001_initial.py
tests/testapp/migrations/__init__.py
tests/testapp/tests/__init__.py
tests/testapp/tests/test_state_machine.py