Metadata-Version: 2.1
Name: deus-state-machina
Version: 0.1.0
Summary: A django state machine, saving you from race-condition sadness
Home-page: https://github.com/TierMobility/deus-state-machina/
Author: Tom Wallroth
Author-email: tomwallroth@gmail.com
License: MIT
Platform: UNKNOWN
Classifier: Programming Language :: Python :: 3.5
Classifier: Programming Language :: Python :: 3.6
Classifier: License :: OSI Approved :: MIT License
Classifier: Development Status :: 5 - Production/Stable
Classifier: Environment :: Web Environment
Classifier: Intended Audience :: Developers
Classifier: Operating System :: OS Independent
